setup.py
eureka/__init__.py
eureka/client.py
eureka/ec2metadata.py
eureka/requests.py
python_eureka.egg-info/PKG-INFO
python_eureka.egg-info/SOURCES.txt
python_eureka.egg-info/dependency_links.txt
python_eureka.egg-info/not-zip-safe
python_eureka.egg-info/requires.txt
python_eureka.egg-info/top_level.txt