Metadata-Version: 1.0
Name: python-eureka
Version: 0.4
Summary: A python interface for Netflix Eureka
Home-page: UNKNOWN
Author: Kristian Øllegaard
Author-email: kristian@oellegaard.com
License: UNKNOWN
Platform: UNKNOWN
